example.py
formal_sdk/__init__.py
formal_sdk/admin.py
formal_sdk/audit.py
formal_sdk/cord.py
formal_sdk/datastore.py
formal_sdk/encryption.py
formal_sdk/etl.py
formal_sdk/identities.py
formal_sdk/integration_app.py
formal_sdk/integration_cloud.py
formal_sdk/integration_code_repository.py
formal_sdk/integration_datahub.py
formal_sdk/integration_external_api.py
formal_sdk/integration_github.py
formal_sdk/integration_incident.py
formal_sdk/integration_kms.py
formal_sdk/integration_log.py
formal_sdk/integration_mfa.py
formal_sdk/integration_slack.py
formal_sdk/integration_sso.py
formal_sdk/inventory.py
formal_sdk/metrics.py
formal_sdk/native_user.py
formal_sdk/outputs.py
formal_sdk/permissions.py
formal_sdk/policies.py
formal_sdk/registry.py
formal_sdk/satellite.py
formal_sdk/search.py
formal_sdk/sidecar.py
formal_sdk/work_os.py
formal_sdk/gen/admin/v1/admin_pb2.py
formal_sdk/gen/admin/v1/admin_pb2.pyi
formal_sdk/gen/admin/v1/admin_pb2_grpc.py
formal_sdk/gen/admin/v1/audit_pb2.py
formal_sdk/gen/admin/v1/audit_pb2.pyi
formal_sdk/gen/admin/v1/audit_pb2_grpc.py
formal_sdk/gen/admin/v1/cord_pb2.py
formal_sdk/gen/admin/v1/cord_pb2.pyi
formal_sdk/gen/admin/v1/cord_pb2_grpc.py
formal_sdk/gen/admin/v1/datastore_pb2.py
formal_sdk/gen/admin/v1/datastore_pb2.pyi
formal_sdk/gen/admin/v1/datastore_pb2_grpc.py
formal_sdk/gen/admin/v1/encryption_pb2.py
formal_sdk/gen/admin/v1/encryption_pb2.pyi
formal_sdk/gen/admin/v1/encryption_pb2_grpc.py
formal_sdk/gen/admin/v1/etl_pb2.py
formal_sdk/gen/admin/v1/etl_pb2.pyi
formal_sdk/gen/admin/v1/etl_pb2_grpc.py
formal_sdk/gen/admin/v1/identities_pb2.py
formal_sdk/gen/admin/v1/identities_pb2.pyi
formal_sdk/gen/admin/v1/identities_pb2_grpc.py
formal_sdk/gen/admin/v1/integration_app_pb2.py
formal_sdk/gen/admin/v1/integration_app_pb2.pyi
formal_sdk/gen/admin/v1/integration_app_pb2_grpc.py
formal_sdk/gen/admin/v1/integration_cloud_pb2.py
formal_sdk/gen/admin/v1/integration_cloud_pb2.pyi
formal_sdk/gen/admin/v1/integration_cloud_pb2_grpc.py
formal_sdk-1.0.48.dist-info/LICENSE
formal_sdk-1.0.48.dist-info/METADATA
formal_sdk-1.0.48.dist-info/WHEEL
formal_sdk-1.0.48.dist-info/top_level.txt
formal_sdk-1.0.48.dist-info/RECORD
