Metadata-Version: 2.2
Name: formal-sdk
Version: 1.0.48
Summary: Formal SDK
Author-email: Formal <hello@joinformal.com>
License: Copyright (c) 2018 The Python Packaging Authority
Project-URL: Homepage, https://github.com/formalco
Classifier: Programming Language :: Python :: 3
Classifier: License :: OSI Approved :: MIT License
Classifier: Operating System :: OS Independent
Requires-Python: >=3.7
License-File: LICENSE
Requires-Dist: requests>=2.26.0
Requires-Dist: beautifulsoup4==4.12.2
Requires-Dist: cachetools==5.3.2
Requires-Dist: certifi==2024.7.4
Requires-Dist: charset-normalizer==3.3.2
Requires-Dist: google==3.0.0
Requires-Dist: google-api-core==2.13.0
Requires-Dist: google-api-python-client==2.107.0
Requires-Dist: google-auth==2.23.4
Requires-Dist: google-auth-httplib2==0.1.1
Requires-Dist: googleapis-common-protos==1.61.0
Requires-Dist: grpcio==1.59.2
Requires-Dist: httplib2==0.22.0
Requires-Dist: idna==3.7
Requires-Dist: protobuf==4.25.0
Requires-Dist: pyasn1==0.5.0
Requires-Dist: pyasn1-modules==0.3.0
Requires-Dist: pyparsing==3.1.1
Requires-Dist: requests==2.31.0
Requires-Dist: rsa==4.9
Requires-Dist: soupsieve==2.5
Requires-Dist: uritemplate==4.1.1
Requires-Dist: urllib3==2.2.2
